feanor/__init__.py
feanor/arbitrary.py
feanor/builtin.py
feanor/engine.py
feanor/library.py
feanor/main.py
feanor/schema.py
feanor/util.py
feanor/dsl/__init__.py
feanor/dsl/_lex_rules.py
feanor/dsl/_parser_rules.py
feanor/dsl/ast.py
feanor/dsl/compiler.py
feanor/dsl/parsetab.py
feanor/dsl/types.py
feanor/types/__init__.py
feanor/types/arbitrary.py
feanor/types/builtin.py
feanor_csv-0.5.0.dist-info/METADATA
feanor_csv-0.5.0.dist-info/RECORD
feanor_csv-0.5.0.dist-info/WHEEL
feanor_csv-0.5.0.dist-info/entry_points.txt
feanor_csv-0.5.0.dist-info/top_level.txt
