Metadata-Version: 2.1
Name: feanor-csv
Version: 0.5.0
Summary: The ultimate CSV artisan.
Home-page: https://github.com/Bakuriu/feanor-csv
Author: Giacomo Alzetta
Author-email: giacomo.alzetta@gmail.com
License: UNKNOWN
Project-URL: Bug Reports, https://github.com/Bakuriu/feanor-csv/issues
Project-URL: Source, https://github.com/Bakuriu/feanor-csv
Keywords: csv generation schema
Platform: UNKNOWN
Classifier: Development Status :: 3 - Alpha
Classifier: Intended Audience :: Developers
Classifier: Topic :: Software Development :: Testing
Classifier: License :: OSI Approved :: Apache Software License
Classifier: Programming Language :: Python :: 3
Classifier: Programming Language :: Python :: 3.6
Provides-Extra: dev
Requires-Dist: ply
Provides-Extra: dev
Requires-Dist: check-manifest; extra == 'dev'
